[
    {
        "PulseType": 0,
        "HomeEzCount": 0,
        "HomeDirection": 2,
        "HomeSpeedMode": 0,
        "HomeLogicLevel": 1,
        "HomeEnableFilter": false,
        "HomeMode": 0,
        "HardwareLimitReaction": 0,
        "HardwareLimitTriggerLevel": 1,
        "AxisId": 0,
        "Name": "x",
        "DecelerationTime": 0.01,
        "MaxWorkSpeed": 20000.0,
        "SoftwareLimitNegativePosition": -73.0,
        "SoftwareLimitPositivePosition": 219.0,
        "WorkSpeed": 4000.0,
        "PulsePerMm": 1000,
        "MinVelocity": 4000,
        "MaxVelocity": 8000,
        "TotalAccelerationTime": 0.5,
        "TotalDecelerationTime": 0.5,
        "PositiveDirectionName": "右",
        "NegativeDirectionName": "左"
    },
    {
        "PulseType": 0,
        "HomeEzCount": 0,
        "HomeDirection": 2,
        "HomeSpeedMode": 0,
        "HomeLogicLevel": 1,
        "HomeEnableFilter": false,
        "HomeMode": 0,
        "HardwareLimitReaction": 0,
        "HardwareLimitTriggerLevel": 1,
        "AxisId": 1,
        "Name": "y",
        "DecelerationTime": 0.5,
        "MaxWorkSpeed": 4000.0,
        "SoftwareLimitNegativePosition": -140.0,
        "SoftwareLimitPositivePosition": 178.0,
        "WorkSpeed": 4000.0,
        "PulsePerMm": 1000,
        "MinVelocity": 4000,
        "MaxVelocity": 8000,
        "TotalAccelerationTime": 0.5,
        "TotalDecelerationTime": 0.5,
        "PositiveDirectionName": "前",
        "NegativeDirectionName": "后"
    }
]